{
    "version": 0,
    "Legal": [
        {
            "year": 0,
            "owner": "_No Owner_",
            "license": "Attribution 4.0 International",
            "artist": "_No Artist_",
            "what": ""
        }
    ],
    "tags": [
        "sharable",
        "no-author",
        "no-owner",
        "no-year",
        "issues"
    ],
    "screenshot": "screenshot\/screenshot.png",
    "name": "SimpleSparseAccessor",
    "path": "https:\/\/github.com\/KhronosGroup\/glTF-Sample-Models\/tree\/master\/.\/2.0\/SimpleSparseAccessor",
    "summary": "A simple mesh that uses sparse accessors",
    "createReadme": false
}